folium_glify_layer/__init__.py
folium_glify_layer/glify_layer.py
folium_glify_layer-0.3.0.dist-info/LICENCE
folium_glify_layer-0.3.0.dist-info/METADATA
folium_glify_layer-0.3.0.dist-info/WHEEL
folium_glify_layer-0.3.0.dist-info/top_level.txt
folium_glify_layer-0.3.0.dist-info/RECORD
