Metadata-Version: 2.1
Name: folium-glify-layer
Version: 0.3.0
Summary: Folium plugin to provide fast webgl rendering for GeoJSON FeatureCollections.
Home-page: https://github.com/onaci/folium-glify-layer
Author: Dan Wild
Author-email: Daniel.Wild@csiro.au
License: UNKNOWN
Platform: UNKNOWN
Classifier: Programming Language :: Python :: 3
Classifier: Programming Language :: Python :: 3.7
